{
  "criteria": {
    "kill_gaia_2": {
      "conditions": {
        "entity": [
          {
            "condition": "minecraft:entity_properties",
            "entity": "this",
            "predicate": {
              "type": "botania:doppleganger",
              "nbt": "{hardMode:1b}"
            }
          }
        ]
      },
      "trigger": "minecraft:player_killed_entity"
    }
  },
  "display": {
    "announce_to_chat": false,
    "background": "botania:textures/block/livingrock_bricks.png",
    "description": {
      "translate": "advancement.megabotany.challenge.desc"
    },
    "frame": "challenge",
    "hidden": false,
    "icon": {
      "item": "megabotany:pandora_box"
    },
    "show_toast": false,
    "title": {
      "translate": "advancement.megabotany.challenge"
    }
  },
  "requirements": [
    [
      "kill_gaia_2"
    ]
  ],
  "sends_telemetry_event": true
}